auto_labeling_pipeline/__init__.py
auto_labeling_pipeline/label.py
auto_labeling_pipeline/labels.py
auto_labeling_pipeline/mappings.py
auto_labeling_pipeline/menu.py
auto_labeling_pipeline/models.py
auto_labeling_pipeline/pipeline.py
auto_labeling_pipeline/postprocessing.py
auto_labeling_pipeline/task.py
auto_labeling_pipeline/templates/amazon_comprehend_entity.jinja2
auto_labeling_pipeline/templates/amazon_comprehend_sentiment.jinja2
auto_labeling_pipeline/templates/amazon_rekognition_label_detection.jinja2
auto_labeling_pipeline/templates/gcp_entities.jinja2
auto_labeling_pipeline/templates/gcp_image_label_detection.jinja2
auto_labeling_pipeline/templates/gcp_speech_to_text.jinja2
auto_labeling_pipeline-0.1.23.dist-info/LICENSE
auto_labeling_pipeline-0.1.23.dist-info/METADATA
auto_labeling_pipeline-0.1.23.dist-info/WHEEL
auto_labeling_pipeline-0.1.23.dist-info/top_level.txt
auto_labeling_pipeline-0.1.23.dist-info/RECORD
