Metadata-Version: 2.1
Name: auto-labeling-pipeline
Version: 0.1.23
Summary: Auto labeling pipeline for doccano
Home-page: https://github.com/doccano/auto-labeling-pipeline
Author: Hironsan
Author-email: hiroki.nakayama.py@gmail.com
License: MIT
Platform: UNKNOWN
Classifier: License :: OSI Approved :: MIT License
Classifier: Programming Language :: Python
Classifier: Programming Language :: Python :: 3.6
Classifier: Programming Language :: Python :: 3.7
Classifier: Programming Language :: Python :: 3.8
Classifier: Programming Language :: Python :: Implementation :: CPython
Classifier: Programming Language :: Python :: Implementation :: PyPy
